py_mercury_switch_api/__init__.py
py_mercury_switch_api/connector.py
py_mercury_switch_api/const.py
py_mercury_switch_api/exceptions.py
py_mercury_switch_api/fetcher.py
py_mercury_switch_api/models.py
py_mercury_switch_api/parsers.py
py_mercury_switch_api/utils.py
py_mercury_switch_api-0.3.0.dist-info/METADATA
py_mercury_switch_api-0.3.0.dist-info/WHEEL
py_mercury_switch_api-0.3.0.dist-info/licenses/LICENSE
py_mercury_switch_api-0.3.0.dist-info/RECORD
