Metadata-Version: 2.4
Name: py-mercury-switch-api
Version: 0.3.0
Summary: A library for interacting with Mercury switches.
Project-URL: Homepage, https://github.com/daxingplay/py-mercury-switch-api
Project-URL: Issues, https://github.com/daxingplay/py-mercury-switch-api/issues
License-File: LICENSE
Keywords: api,library,mercury,switch
Classifier: License :: OSI Approved :: Apache Software License
Classifier: Operating System :: OS Independent
Classifier: Programming Language :: Python :: 3
Requires-Python: >=3.9
Requires-Dist: requests
